goat_plugins/opensea/__init__.py
goat_plugins/opensea/parameters.py
goat_plugins/opensea/service.py
goat_sdk_plugin_opensea-0.1.1.dist-info/METADATA
goat_sdk_plugin_opensea-0.1.1.dist-info/WHEEL
goat_sdk_plugin_opensea-0.1.1.dist-info/RECORD
